entity/entities.py
entity/entity.py
entity/infer_id.py
entity/kr_db.py
entity/kraken_json.py
entity/normalize.py
entity/observation.py
entity/observations.py
entity/schema_org.py
kr_entity-0.0.23.dist-info/LICENSE.txt
kr_entity-0.0.23.dist-info/METADATA
kr_entity-0.0.23.dist-info/WHEEL
kr_entity-0.0.23.dist-info/top_level.txt
kr_entity-0.0.23.dist-info/RECORD
