Metadata-Version: 2.1
Name: kr-entity
Version: 0.0.23
Summary: Kraken Entities
Home-page: https://github.com/tactik8/entity
Author: Tactik8
Author-email: info@tactik8.com
License: MIT
Platform: UNKNOWN
Classifier: License :: OSI Approved :: MIT License
Classifier: Programming Language :: Python :: 3
Classifier: Programming Language :: Python :: 3.8
License-File: LICENSE.txt
Requires-Dist: tabulate
Requires-Dist: email-normalize
Requires-Dist: url-normalize
Requires-Dist: pycountry
Requires-Dist: phonenumbers
Requires-Dist: cleanco
